django_form_button/__init__.py
django_form_button/decorators.py
django_form_button/mixins.py
django_form_button/py.typed
django_form_button-1.0.0.dist-info/LICENSE
django_form_button-1.0.0.dist-info/METADATA
django_form_button-1.0.0.dist-info/WHEEL
django_form_button-1.0.0.dist-info/top_level.txt
django_form_button-1.0.0.dist-info/RECORD
