Metadata-Version: 2.1
Name: django-form-button
Version: 1.0.0
Summary: Django admin extra buttons with form
Author-email: Pradish Bijukchhe <pradishbijukchhe@gmail.com>
License: Copyright (c) 2018 The Python Packaging Authority
Project-URL: Homepage, https://github.com/sandbox-pokhara/django-form-button
Project-URL: Issues, https://github.com/sandbox-pokhara/django-form-button/issues
Classifier: Programming Language :: Python :: 3
Requires-Python: >=3
License-File: LICENSE
Requires-Dist: django
